{
  "json_md_fusion_scroll": {
    "timestamp": "2025-08-11T10:19:52.669Z",
    "source_text_length": 1294,
    "word_count": 113,
    "entropy_level": "0.607",
    "contradictions_detected": 0,
    "processing_phase": "FUSION",
    "frequency_resonance": "659.25 Hz (E5)",
    "format": "json_md_fusion",
    "anchor_id": "6f4e49a264f0fc38f8b3412476a3eb1dc3872643d6523c6e68d2a7815ce6c05e"
  },
  "content_analysis": {
    "contradictions": 0,
    "entropy": 0.6071209620381526,
    "wordCount": 113,
    "anchor": "6f4e49a264f0fc38f8b3412476a3eb1dc3872643d6523c6e68d2a7815ce6c05e"
  }
}