{
  "json_md_fusion_scroll": {
    "timestamp": "2025-08-11T10:19:19.708Z",
    "source_text_length": 5292,
    "word_count": 476,
    "entropy_level": "0.774",
    "contradictions_detected": 8,
    "processing_phase": "FUSION",
    "frequency_resonance": "659.25 Hz (E5)",
    "format": "json_md_fusion",
    "anchor_id": "aad087b4f18a90cce17178f3646db9aaefdb24195b4e453e4bc319e5a769afa6"
  },
  "content_analysis": {
    "contradictions": 8,
    "entropy": 0.7739536108976529,
    "wordCount": 476,
    "anchor": "aad087b4f18a90cce17178f3646db9aaefdb24195b4e453e4bc319e5a769afa6"
  }
}