{
  "json_md_fusion_scroll": {
    "timestamp": "2025-08-11T10:20:00.893Z",
    "source_text_length": 1321,
    "word_count": 100,
    "entropy_level": "0.602",
    "contradictions_detected": 0,
    "processing_phase": "FUSION",
    "frequency_resonance": "659.25 Hz (E5)",
    "format": "json_md_fusion",
    "anchor_id": "1e8d029c49f8beb617352d3cb7611540ad716d4039052353f6371cd15c6c53f9"
  },
  "content_analysis": {
    "contradictions": 0,
    "entropy": 0.6015077213803628,
    "wordCount": 100,
    "anchor": "1e8d029c49f8beb617352d3cb7611540ad716d4039052353f6371cd15c6c53f9"
  }
}