{
  "json_md_fusion_scroll": {
    "timestamp": "2025-08-11T10:20:18.042Z",
    "source_text_length": 5763,
    "word_count": 214,
    "entropy_level": "0.723",
    "contradictions_detected": 19,
    "processing_phase": "FUSION",
    "frequency_resonance": "659.25 Hz (E5)",
    "format": "json_md_fusion",
    "anchor_id": "54778741cbb7c899f00459360911a037e33992e64ddfe3979b38c81a4132f049"
  },
  "content_analysis": {
    "contradictions": 19,
    "entropy": 0.7230682756792406,
    "wordCount": 214,
    "anchor": "54778741cbb7c899f00459360911a037e33992e64ddfe3979b38c81a4132f049"
  }
}