{
  "json_md_fusion_scroll": {
    "timestamp": "2025-08-11T10:19:18.033Z",
    "source_text_length": 2184,
    "word_count": 113,
    "entropy_level": "0.611",
    "contradictions_detected": 1,
    "processing_phase": "FUSION",
    "frequency_resonance": "659.25 Hz (E5)",
    "format": "json_md_fusion",
    "anchor_id": "098fcedac83f8ac6bace9d519de7dca15d1f9833a51b4a4c0d83d4af11726851"
  },
  "content_analysis": {
    "contradictions": 1,
    "entropy": 0.6111432384506322,
    "wordCount": 113,
    "anchor": "098fcedac83f8ac6bace9d519de7dca15d1f9833a51b4a4c0d83d4af11726851"
  }
}