{
  "json_md_fusion_scroll": {
    "timestamp": "2025-08-11T10:19:28.752Z",
    "source_text_length": 67358,
    "word_count": 8391,
    "entropy_level": "0.912",
    "contradictions_detected": 150,
    "processing_phase": "FUSION",
    "frequency_resonance": "659.25 Hz (E5)",
    "format": "json_md_fusion",
    "anchor_id": "0b0ac00fa554de6dcf4eea6306ea56be329a40136d769e48e65ecf5faca086db"
  },
  "content_analysis": {
    "contradictions": 150,
    "entropy": 0.9123848358993442,
    "wordCount": 8391,
    "anchor": "0b0ac00fa554de6dcf4eea6306ea56be329a40136d769e48e65ecf5faca086db"
  }
}