{
  "json_md_fusion_scroll": {
    "timestamp": "2025-08-11T10:19:54.221Z",
    "source_text_length": 2142,
    "word_count": 224,
    "entropy_level": "0.657",
    "contradictions_detected": 7,
    "processing_phase": "FUSION",
    "frequency_resonance": "659.25 Hz (E5)",
    "format": "json_md_fusion",
    "anchor_id": "a4e9ef0355e5b6e02f9e54a1cea333a8fd392259d63365591b47d93eb22eeb5c"
  },
  "content_analysis": {
    "contradictions": 7,
    "entropy": 0.65717130881043,
    "wordCount": 224,
    "anchor": "a4e9ef0355e5b6e02f9e54a1cea333a8fd392259d63365591b47d93eb22eeb5c"
  }
}