{
  "json_md_fusion_scroll": {
    "timestamp": "2025-08-11T10:19:00.480Z",
    "source_text_length": 6237,
    "word_count": 365,
    "entropy_level": "0.703",
    "contradictions_detected": 6,
    "processing_phase": "FUSION",
    "frequency_resonance": "659.25 Hz (E5)",
    "format": "json_md_fusion",
    "anchor_id": "da7961c47009691bbb5680aba00322d9f4255e43872e468c6078d50201e08951"
  },
  "content_analysis": {
    "contradictions": 6,
    "entropy": 0.7031254032584108,
    "wordCount": 365,
    "anchor": "da7961c47009691bbb5680aba00322d9f4255e43872e468c6078d50201e08951"
  }
}