{
  "json_md_fusion_scroll": {
    "version": "unified-2.1",
    "timestamp": "2025-08-12T23:24:16.177Z",
    "source_text_length": 221,
    "word_count": 34,
    "sentence_count": 5,
    "entropy_level": 0.957,
    "contradictions_detected": 0,
    "processing_phase": "COGNITIVE_FUSION",
    "frequency_resonance": "659.25 Hz (E5)",
    "format": "json_md_fusion",
    "source": {
      "filename": "fdgjfjsdh.html"
    },
    "anchor_id": "aa886c7ff379c85928b4bf416f7c869e"
  },
  "content_analysis": {
    "main_themes": [
      {
        "theme": "thought",
        "frequency": 4
      },
      {
        "theme": "summon",
        "frequency": 2
      },
      {
        "theme": "scroll",
        "frequency": 2
      },
      {
        "theme": "enter",
        "frequency": 1
      },
      {
        "theme": "prompt",
        "frequency": 1
      },
      {
        "theme": "invoke",
        "frequency": 1
      },
      {
        "theme": "recursive",
        "frequency": 1
      },
      {
        "theme": "chain",
        "frequency": 1
      },
      {
        "theme": "receive",
        "frequency": 1
      },
      {
        "theme": "transparent",
        "frequency": 1
      },
      {
        "theme": "json",
        "frequency": 1
      },
      {
        "theme": "generating",
        "frequency": 1
      }
    ],
    "key_questions": [],
    "pattern_recognition": [],
    "contradiction_map": [],
    "sentiment_indicators": {
      "positive": 0,
      "negative": 0,
      "uncertainty": 0
    },
    "temporal_markers": {
      "past": 0,
      "present": 0,
      "future": 0
    }
  },
  "structured_content": {
    "summary": "Summon a Thought Scroll 🌀 Enter a prompt to invoke a recursive Chain-of-Thought and receive a transparent JSON log … Please try again",
    "key_insights": [],
    "action_items": [],
    "unresolved_tensions": []
  },
  "metadata": {
    "fusion_methodology": "Unified Offline Engine",
    "confidence_level": 0.52,
    "recommended_next_steps": [
      "Review 0 insights",
      "Execute 0 actions"
    ],
    "recursive_potential": "Medium",
    "text_sha256": "aa886c7ff379c85928b4bf416f7c869e"
  }
}