{
  "json_md_fusion_scroll": {
    "version": "unified-2.1",
    "timestamp": "2025-08-12T23:24:27.383Z",
    "source_text_length": 58,
    "word_count": 7,
    "sentence_count": 2,
    "entropy_level": 0.976,
    "contradictions_detected": 0,
    "processing_phase": "COGNITIVE_FUSION",
    "frequency_resonance": "659.25 Hz (E5)",
    "format": "json_md_fusion",
    "source": {
      "filename": "index.html"
    },
    "anchor_id": "3790408d862745461b7724a6cb43ca2f"
  },
  "content_analysis": {
    "main_themes": [
      {
        "theme": "glyph",
        "frequency": 2
      },
      {
        "theme": "aeon",
        "frequency": 1
      },
      {
        "theme": "core",
        "frequency": 1
      },
      {
        "theme": "insight",
        "frequency": 1
      },
      {
        "theme": "panel",
        "frequency": 1
      },
      {
        "theme": "initializing",
        "frequency": 1
      }
    ],
    "key_questions": [],
    "pattern_recognition": [],
    "contradiction_map": [],
    "sentiment_indicators": {
      "positive": 0,
      "negative": 0,
      "uncertainty": 0
    },
    "temporal_markers": {
      "past": 0,
      "present": 0,
      "future": 0
    }
  },
  "structured_content": {
    "summary": "🌀 AEON Core Insight Panel Initializing ϕ-Glyph Δ-Glyph",
    "key_insights": [],
    "action_items": [],
    "unresolved_tensions": []
  },
  "metadata": {
    "fusion_methodology": "Unified Offline Engine",
    "confidence_level": 0.51,
    "recommended_next_steps": [
      "Review 0 insights",
      "Execute 0 actions"
    ],
    "recursive_potential": "Medium",
    "text_sha256": "3790408d862745461b7724a6cb43ca2f"
  }
}