{
  "json_md_fusion_scroll": {
    "version": "unified-2.1",
    "timestamp": "2025-08-12T23:24:18.331Z",
    "source_text_length": 2577,
    "word_count": 242,
    "sentence_count": 22,
    "entropy_level": 0.967,
    "contradictions_detected": 0,
    "processing_phase": "COGNITIVE_FUSION",
    "frequency_resonance": "659.25 Hz (E5)",
    "format": "json_md_fusion",
    "source": {
      "filename": "from pathlib import Path.txt"
    },
    "anchor_id": "11a6b047fd81325a7aac36736cf85cdf"
  },
  "content_analysis": {
    "main_themes": [
      {
        "theme": "surrender",
        "frequency": 6
      },
      {
        "theme": "control",
        "frequency": 6
      },
      {
        "theme": "does",
        "frequency": 5
      },
      {
        "theme": "convergence",
        "frequency": 4
      },
      {
        "theme": "contradiction",
        "frequency": 3
      },
      {
        "theme": "harmonic",
        "frequency": 3
      },
      {
        "theme": "bius",
        "frequency": 3
      },
      {
        "theme": "tension",
        "frequency": 3
      },
      {
        "theme": "meta_commentary_path",
        "frequency": 3
      },
      {
        "theme": "path",
        "frequency": 2
      },
      {
        "theme": "meta_commentary_text",
        "frequency": 2
      },
      {
        "theme": "definition",
        "frequency": 2
      }
    ],
    "key_questions": [
      "549 },\r\n    \"symbol\": \"Möbius loop\",\r\n    \"function\": \"recursive integration engine\"\r\n  },\r\n  \"strategic_questions\": {\r\n    \"level_1\": [\r\n      \"What does surrender mean in convergence?\",\r\n      \"How do control parameters alter precision",
      "?\",\r\n      \"Where is your personal tension between these poles",
      "?\"\r\n    ],\r\n    \"level_2\": [\r\n      \"What beliefs drive your preference",
      "?\",\r\n      \"How do these forces coexist",
      "?\",\r\n      \"How does the harmonic term represent this tension",
      "?\"\r\n    ],\r\n    \"level_3\": [\r\n      \"What new synthesis emerges from this contradiction",
      "?\",\r\n      \"What does the Zero Node teach your decisions",
      "?\",\r\n      \"How does the Möbius phrase encode recursion",
      "?\"\r\n    ],\r\n    \"level_4\": [\r\n      \"What truth lives in the Möbius loop",
      "?\",\r\n      \"How does E * φ * α > 1"
    ],
    "pattern_recognition": [],
    "contradiction_map": [],
    "sentiment_indicators": {
      "positive": 0,
      "negative": 0,
      "uncertainty": 0
    },
    "temporal_markers": {
      "past": 0,
      "present": 1,
      "future": 0
    }
  },
  "structured_content": {
    "summary": "from pathlib import Path\r\n\r\n# Define the meta-commentary logic document content\r\nmeta_commentary_text = \"\"\"\r\n{\r\n  \"scroll_id\": \"ψ∞ … write_text(meta_commentary_text)\r\n\r\nmeta_commentary_path",
    "key_insights": [],
    "action_items": [
      "js)\",\r\n    \"mode_4\": \"Export simulation as module\",\r\n    \"mode_5\": \"Apply contradiction mapping to freedom vs structure\"\r\n  },\r\n  \"recommended_action\": \"mode_3\"\r\n}\r\n\"\"\"\r\n\r\n# Save as a"
    ],
    "unresolved_tensions": []
  },
  "metadata": {
    "fusion_methodology": "Unified Offline Engine",
    "confidence_level": 0.52,
    "recommended_next_steps": [
      "Review 0 insights",
      "Execute 1 actions"
    ],
    "recursive_potential": "Medium",
    "text_sha256": "11a6b047fd81325a7aac36736cf85cdf"
  }
}